Verilog/SRAM/ssram.v
`timescale 1ns/1ps

module ssram #(
    parameter ADDR_WIDTH = 4,
    parameter DATA_WIDTH = 8,
    parameter DEPTH = 16
)(
    input                       CLK,
    input                       CS,
    input                       ADS_L,
    input                       GW_L,
    input                       OE,
    input      [ADDR_WIDTH-1:0] ADDR,
    inout      [DATA_WIDTH-1:0] DIO
);

// Internal Memory Array

reg [DATA_WIDTH-1:0] SRAM_array [0:DEPTH-1];


// Internal Registers

reg [ADDR_WIDTH-1:0] AREG;
reg                  CREG;
reg [DATA_WIDTH-1:0] INREG;
reg [DATA_WIDTH-1:0] OUTREG;


// Internal Signals

reg [DATA_WIDTH-1:0] DOUT;
reg                  write_enable;
reg                  read_enable;


// Bidirectional Data Bus

assign DIO = (CS && OE && !GW_L) ? {DATA_WIDTH{1'bz}} :
             (CS && OE && GW_L)  ? OUTREG :
             {DATA_WIDTH{1'bz}};


// Address Register (AREG)

always @(posedge CLK)
begin
    if(CS && !ADS_L)
    begin
        AREG <= ADDR;
    end
end


// Control Register (CREG)

always @(posedge CLK)
begin
    if(CS)
    begin
        CREG <= GW_L;
    end
end


// Input Register (INREG)

always @(posedge CLK)
begin
    if(CS && !GW_L)
    begin
        INREG <= DIO;
    end
end


// Write Operation

always @(posedge CLK)
begin
    if(CS && !GW_L)
    begin
        SRAM_array[AREG] <= INREG;
    end
end


// Read Operation

always @(posedge CLK)
begin
    if(CS && GW_L)
    begin
        DOUT <= SRAM_array[AREG];
    end
end


// Output Register (OUTREG)

always @(posedge CLK)
begin
    if(CS && GW_L)
    begin
        OUTREG <= DOUT;
    end
end

endmodule

Verilog/SRAM/ssram_tb.v
`timescale 1ns/1ps

module ssram_tb;

parameter ADDR_WIDTH = 4;
parameter DATA_WIDTH = 8;

reg CLK;
reg CS;
reg ADS_L;
reg GW_L;
reg OE;
reg [ADDR_WIDTH-1:0] ADDR;

wire [DATA_WIDTH-1:0] DIO;

reg  [DATA_WIDTH-1:0] drive_data;
reg                   drive_enable;

//--------------------------------------------------
// Bidirectional Bus Driver
//--------------------------------------------------
assign DIO = (drive_enable) ? drive_data : 8'bz;

//--------------------------------------------------
// DUT
//--------------------------------------------------
ssram uut (
    .CLK(CLK),
    .CS(CS),
    .ADS_L(ADS_L),
    .GW_L(GW_L),
    .OE(OE),
    .ADDR(ADDR),
    .DIO(DIO)
);

//--------------------------------------------------
// Clock Generation
//--------------------------------------------------
initial
begin
    CLK = 0;
    forever #5 CLK = ~CLK;
end

//--------------------------------------------------
// Stimulus
//--------------------------------------------------
initial
begin

    //--------------------------------------------------
    // Initialize
    //--------------------------------------------------
    CS = 0;
    ADS_L = 1;
    GW_L = 1;
    OE = 0;
    ADDR = 0;

    drive_data = 0;
    drive_enable = 0;

    //--------------------------------------------------
    // VCD Dump
    //--------------------------------------------------
    $dumpfile("ssram.vcd");
    $dumpvars(0, ssram_tb);

    //--------------------------------------------------
    // Start Device
    //--------------------------------------------------
    #20;

    CS = 1;
    OE = 1;

    //--------------------------------------------------
    // WRITE OPERATION
    //--------------------------------------------------

    @(posedge CLK);
    ADS_L = 0;
    GW_L  = 0;
    ADDR  = 4'b0011;

    drive_enable = 1;
    drive_data   = 8'hA5;

    @(posedge CLK);
    ADS_L = 1;

    @(posedge CLK);
    GW_L = 1;
    drive_enable = 0;

    //--------------------------------------------------
    // READ OPERATION
    //--------------------------------------------------

    @(posedge CLK);
    ADS_L = 0;
    GW_L  = 1;
    ADDR  = 4'b0011;

    @(posedge CLK);
    ADS_L = 1;

    //--------------------------------------------------
    // Additional Reads
    //--------------------------------------------------

    @(posedge CLK);
    ADDR = 4'b0100;

    @(posedge CLK);
    ADDR = 4'b0101;

    //--------------------------------------------------
    // Finish
    //--------------------------------------------------

    #100;
    $finish;

end

endmodule

Verilog/SRAM/ssram.vcd
$date
   Sun May 10 16:10:22 2026
$end

$version
  2025.2
  $dumpfile ("ssram.vcd") 
$end

$timescale
  1ps
$end

$scope module ssram_tb $end
$var reg 1 ! CLK $end
$var reg 1 " CS $end
$var reg 1 # ADS_L $end
$var reg 1 $ GW_L $end
$var reg 1 % OE $end
$var reg 4 & ADDR [3:0] $end
$var wire 8 ' DIO [7:0] $end
$var reg 8 ( drive_data [7:0] $end
$var reg 1 ) drive_enable $end
$scope module uut $end
$var wire 1 * CLK $end
$var wire 1 + CS $end
$var wire 1 , ADS_L $end
$var wire 1 - GW_L $end
$var wire 1 . OE $end
$var wire 4 / ADDR [3:0] $end
$var wire 8 ' DIO [7:0] $end
$var reg 4 0 AREG [3:0] $end
$var reg 1 1 CREG $end
$var reg 8 2 INREG [7:0] $end
$var reg 8 3 OUTREG [7:0] $end
$var reg 8 4 DOUT [7:0] $end
$var reg 1 5 write_enable $end
$var reg 1 6 read_enable $end
$upscope $end
$upscope $end
$enddefinitions $end

#0
$dumpvars
0!
0"
1#
1$
0%
b0 &
bz '
b0 (
0)
0*
0+
1,
1-
0.
b0 /
bx 0
x1
bx 2
bx 3
bx 4
x5
x6
$end

#5000
1!
1*

#10000
0!
0*

#15000
1!
1*

#20000
0!
1"
1%
bx '
0*
1+
1.

#25000
1!
0#
0$
b11 &
b10100101 '
b10100101 (
1)
1*
0,
0-
b11 /
b11 0
01

#30000
0!
0*

#35000
1!
1#
1*
1,
b10100101 2

#40000
0!
0*

#45000
1!
1$
bx '
0)
1*
1-
11

#50000
0!
0*

#55000
1!
0#
1*
0,

#60000
0!
0*

#65000
1!
1#
1*
1,

#70000
0!
0*

#75000
1!
b100 &
1*
b100 /

#80000
0!
0*

#85000
1!
b101 &
1*
b101 /

